setup.cfg
setup.py
beer/__init__.py
beer/cli.py
beer/process.py
beer_review.egg-info/PKG-INFO
beer_review.egg-info/SOURCES.txt
beer_review.egg-info/dependency_links.txt
beer_review.egg-info/entry_points.txt
beer_review.egg-info/not-zip-safe
beer_review.egg-info/pbr.json
beer_review.egg-info/requires.txt
beer_review.egg-info/top_level.txt