Metadata-Version: 1.1
Name: beer-review
Version: 0.3.0
Summary: CLI for managing your JIRA / Gerrit / git workflow.
Home-page: https://github.com/kunickiaj/beer-review
Author: Adam Kunicki
Author-email: kunickiaj@gmail.com
License: MIT
Platform: any
Classifier: Development Status :: 3 - Alpha
Classifier: Environment :: Console
Classifier: Intended Audience :: Developers
Classifier: License :: OSI Approved :: MIT License
Classifier: Operating System :: POSIX
Classifier: Operating System :: MacOS
Classifier: Operating System :: Unix
Classifier: Programming Language :: Python
Classifier: Programming Language :: Python :: 3
Classifier: Topic :: Software Development :: Libraries :: Python Modules
